pygravity/__init__.py
pygravity/math.cp39-win_amd64.pyd
pygravity/math.pyi
pygravity/py.typed
pygravity/twod/__init__.py
pygravity/twod/gravity.cp39-win_amd64.pyd
pygravity/twod/gravity.pyi
pygravity/twod/physics.cp39-win_amd64.pyd
pygravity/twod/physics.pyi
pygravity/twod/py.typed
pygravity/twod/pygame_simulation.py
pygravity/twod/util.py
pygravity/twod/vector.cp39-win_amd64.pyd
pygravity/twod/vector.pyi
Python_Gravity-1.0.2.dist-info/LICENSE
Python_Gravity-1.0.2.dist-info/METADATA
Python_Gravity-1.0.2.dist-info/WHEEL
Python_Gravity-1.0.2.dist-info/top_level.txt
Python_Gravity-1.0.2.dist-info/RECORD
