Metadata-Version: 2.1
Name: Python-Gravity
Version: 1.0.2
Summary: Library for calculating stuff having to do with gravity
Home-page: https://github.com/gaming32/pygravity
Author: Gaming32
Author-email: gaming32i64@gmail.com
License: License :: OSI Approved :: MIT License
Platform: UNKNOWN
